pydantic_ai_toolsets/__init__.py
pydantic_ai_toolsets/evals/__init__.py
pydantic_ai_toolsets/evals/base.py
pydantic_ai_toolsets/evals/config.py
pydantic_ai_toolsets/evals/evaluators.py
pydantic_ai_toolsets/evals/run_evals.py
pydantic_ai_toolsets/evals/categories/__init__.py
pydantic_ai_toolsets/evals/categories/combinations/__init__.py
pydantic_ai_toolsets/evals/categories/combinations/code_architect_eval.py
pydantic_ai_toolsets/evals/categories/combinations/compare_combinations.py
pydantic_ai_toolsets/evals/categories/combinations/creative_problem_solver_eval.py
pydantic_ai_toolsets/evals/categories/combinations/research_assistant_eval.py
pydantic_ai_toolsets/evals/categories/combinations/strategic_decision_maker_eval.py
pydantic_ai_toolsets/evals/categories/multi_agent/__init__.py
pydantic_ai_toolsets/evals/categories/multi_agent/compare_multi_agent.py
pydantic_ai_toolsets/evals/categories/multi_agent/multi_personas_eval.py
pydantic_ai_toolsets/evals/categories/multi_agent/persona_debate_eval.py
pydantic_ai_toolsets/evals/categories/reflection/__init__.py
pydantic_ai_toolsets/evals/categories/reflection/compare_reflection.py
pydantic_ai_toolsets/evals/categories/reflection/reflection_eval.py
pydantic_ai_toolsets/evals/categories/reflection/self_ask_eval.py
pydantic_ai_toolsets/evals/categories/reflection/self_refine_eval.py
pydantic_ai_toolsets/evals/categories/thinking_cognition/__init__.py
pydantic_ai_toolsets/evals/categories/thinking_cognition/beam_eval.py
pydantic_ai_toolsets/evals/categories/thinking_cognition/compare_thinking.py
pydantic_ai_toolsets/evals/categories/thinking_cognition/cot_eval.py
pydantic_ai_toolsets/evals/categories/thinking_cognition/got_eval.py
pydantic_ai_toolsets/evals/categories/thinking_cognition/mcts_eval.py
pydantic_ai_toolsets/evals/categories/thinking_cognition/tot_eval.py
pydantic_ai_toolsets/evals/categories/uniques/__init__.py
pydantic_ai_toolsets/evals/categories/uniques/search_eval.py
pydantic_ai_toolsets-0.3.1.dist-info/METADATA
pydantic_ai_toolsets-0.3.1.dist-info/WHEEL
pydantic_ai_toolsets-0.3.1.dist-info/licenses/LICENSE
pydantic_ai_toolsets-0.3.1.dist-info/RECORD
