Metadata-Version: 2.4
Name: pydantic-ai-toolsets
Version: 0.3.1
Summary: Combine or use individual toolsets to give super powers to your Pydantic AI agents.
Project-URL: Homepage, https://pydantic-ai-toolsets.readthedocs.io/en/latest/
Project-URL: Documentation, https://pydantic-ai-toolsets.readthedocs.io/en/latest/
Project-URL: Source, https://github.com/vintageshinpads/pydantic_ai_toolsets
Project-URL: Issues, https://github.com/vintageshinpads/pydantic_ai_toolsets/issues
Author-email: Shreyans Maini <shreyansmaini@gmail.com>
License: MIT
License-File: LICENSE
Requires-Python: >=3.12
Requires-Dist: firecrawl>=4.13.1
Requires-Dist: logfire>=4.19.0
Requires-Dist: myst-parser>=5.0.0
Requires-Dist: pydantic-ai[logfire]>=1.44.0
Requires-Dist: pydantic-evals[logfire]>=1.44.0
Requires-Dist: pydantic>=2.12.5
Requires-Dist: sphinx-rtd-theme>=3.1.0
Requires-Dist: sphinx>=9.1.0
Requires-Dist: trafilatura>=2.0.0
Provides-Extra: docs
Requires-Dist: myst-parser>=5.0.0; extra == 'docs'
Requires-Dist: sphinx-conestack-theme>=1.1.0; extra == 'docs'
Requires-Dist: sphinx>=9.1.0; extra == 'docs'
Provides-Extra: test
Requires-Dist: hypothesis>=6.92.0; extra == 'test'
Requires-Dist: pytest-asyncio>=0.23.0; extra == 'test'
Requires-Dist: pytest-cov>=4.1.0; extra == 'test'
Requires-Dist: pytest-mock>=3.12.0; extra == 'test'
Requires-Dist: pytest>=8.0.0; extra == 'test'
